idle_term/__init__.py
idle_term/idle_term.py
idle_term/outputwindow_write.py
idle_term/pyshell_write.py
idle_term-1.0.0.post3.dist-info/METADATA
idle_term-1.0.0.post3.dist-info/WHEEL
idle_term-1.0.0.post3.dist-info/RECORD
