Metadata-Version: 2.4
Name: idle-term
Version: 1.0.0.post3
Summary: A library providing some terminal features for IDLE's shell
Project-URL: Homepage, https://github.com/pyhacks/idle-term
Author-email: pyhacks <enginyildirim111@gmail.com>
Keywords: idle,progressbar,terminal
Requires-Dist: hypno
Requires-Dist: psutil
